nsj_integracao_api_client/__init__.py
nsj_integracao_api_client/client_console.py
nsj_integracao_api_client/app/__init__.py
nsj_integracao_api_client/app/ui/__init__.py
nsj_integracao_api_client/app/ui/acompanhamento.py
nsj_integracao_api_client/app/ui/aplicacao.py
nsj_integracao_api_client/app/ui/ativacao.py
nsj_integracao_api_client/app/ui/browser_execucoes.py
nsj_integracao_api_client/app/ui/browser_execucoes_detail.py
nsj_integracao_api_client/app/ui/carga_continua.py
nsj_integracao_api_client/app/ui/carga_inicial.py
nsj_integracao_api_client/app/ui/checkable_combobox.py
nsj_integracao_api_client/app/ui/conf_carga_continua.py
nsj_integracao_api_client/app/ui/config_inicial.py
nsj_integracao_api_client/app/ui/configuracoes_gerais.py
nsj_integracao_api_client/app/ui/configurada.py
nsj_integracao_api_client/app/ui/integracao.py
nsj_integracao_api_client/app/ui/integridade.py
nsj_integracao_api_client/app/ui/main.py
nsj_integracao_api_client/app/ui/mensagem.py
nsj_integracao_api_client/app/ui/painel_controle.py
nsj_integracao_api_client/app/ui/pendencias.py
nsj_integracao_api_client/app/ui/pendencias_detalhes.py
nsj_integracao_api_client/app/ui/status.py
nsj_integracao_api_client/app/ui/verificacao_integridade.py
nsj_integracao_api_client/dao/__init__.py
nsj_integracao_api_client/dao/integracao.py
nsj_integracao_api_client/dao/job.py
nsj_integracao_api_client/dto/__init__.py
nsj_integracao_api_client/entity/__init__.py
nsj_integracao_api_client/infra/__init__.py
nsj_integracao_api_client/infra/api_client.py
nsj_integracao_api_client/infra/debug_utils.py
nsj_integracao_api_client/infra/injector_factory.py
nsj_integracao_api_client/infra/token_service.py
nsj_integracao_api_client/infra/transform.py
nsj_integracao_api_client/infra/telemetria/__init__.py
nsj_integracao_api_client/infra/telemetria/campos_fixos.py
nsj_integracao_api_client/infra/telemetria/config.py
nsj_integracao_api_client/infra/telemetria/factory.py
nsj_integracao_api_client-2.2502.0.26.dist-info/METADATA
nsj_integracao_api_client-2.2502.0.26.dist-info/WHEEL
nsj_integracao_api_client-2.2502.0.26.dist-info/top_level.txt
nsj_integracao_api_client-2.2502.0.26.dist-info/RECORD
