Metadata-Version: 2.4
Name: nsj_integracao_api_client
Version: 2.2502.0.26
Summary: Client em Python desenvolvido para facilitar a extração de dados de bancos de dados de ERPs e a integração com as APIs de integração da Nasajon. Ele automatiza o fluxo de comunicação entre sistemas, oferecendo funcionalidades para consulta, transformação e envio de dados de maneira eficiente.
Home-page: https://github.com/Nasajon/nsj_integracao_api_client
Author: Nasajon Sistemas
Author-email: contact.dev@nasajon.com.br
Project-URL: Source, https://github.com/Nasajon/nsj_integracao_api_client
Classifier: Development Status :: 3 - Alpha
Classifier: Intended Audience :: Developers
Classifier: Topic :: Software Development :: Libraries
Classifier: Programming Language :: Python :: 3
Requires-Python: >=3.4
Requires-Dist: nsj-integracao-api-entidades==1.0.0a25-46
Requires-Dist: colorama==0.4.6
Requires-Dist: tzdata==2025.1
Requires-Dist: PyQt5==5.15.11
Requires-Dist: sentry-sdk==1.7.1
Requires-Dist: psutil>=5.9.0
